README.md
setup.py
myNeuropsydia/__init__.py
myNeuropsydia/ask.py
myNeuropsydia/choice.py
myNeuropsydia/core.py
myNeuropsydia/fill_form.py
myNeuropsydia/image.py
myNeuropsydia/io.py
myNeuropsydia/meta.py
myNeuropsydia/miscellaneous.py
myNeuropsydia/path.py
myNeuropsydia/procedures.py
myNeuropsydia/scale.py
myNeuropsydia/screen.py
myNeuropsydia/start.py
myNeuropsydia/write.py
myNeuropsydia/files/__init__.py
myNeuropsydia/files/binary/__init__.py
myNeuropsydia/files/binary/absorption_desk.png
myNeuropsydia/files/binary/absorption_man.png
myNeuropsydia/files/binary/cursor_absorption.png
myNeuropsydia/files/binary/cursor_absorption_validated.png
myNeuropsydia/files/binary/cursor_blue.png
myNeuropsydia/files/binary/cursor_blue_validated.png
myNeuropsydia/files/binary/cursor_green.png
myNeuropsydia/files/binary/cursor_green_validated.png
myNeuropsydia/files/binary/cursor_orange.png
myNeuropsydia/files/binary/cursor_orange_validated.png
myNeuropsydia/files/binary/cursor_purple.png
myNeuropsydia/files/binary/cursor_purple_validated.png
myNeuropsydia/files/binary/cursor_red.png
myNeuropsydia/files/binary/cursor_red_validated.png
myNeuropsydia/files/binary/cursor_teal.png
myNeuropsydia/files/binary/cursor_teal_validated.png
myNeuropsydia/files/binary/cursor_yellow.png
myNeuropsydia/files/binary/cursor_yellow_validated.png
myNeuropsydia/files/binary/scale_point.png
myNeuropsydia/files/font/LiberationMono-Bold.ttf
myNeuropsydia/files/font/LiberationMono-Regular.ttf
myNeuropsydia/files/font/RobotoBlack.ttf
myNeuropsydia/files/font/RobotoBold.ttf
myNeuropsydia/files/font/RobotoLight.ttf
myNeuropsydia/files/font/RobotoRegular.ttf
myNeuropsydia/files/font/Timeless-Bold.ttf
myNeuropsydia/files/font/Timeless.ttf
myNeuropsydia/files/font/__init__.py
myNeuropsydia/files/logo/N.png
myNeuropsydia/files/logo/Neuropsydia_HEAD_white.png
myNeuropsydia/files/logo/Neuropsydia_PSY_blue.png
myNeuropsydia/files/logo/Neuropsydia_TEXT_white.png
myNeuropsydia/files/logo/Python.png
myNeurospydia.egg-info/PKG-INFO
myNeurospydia.egg-info/SOURCES.txt
myNeurospydia.egg-info/dependency_links.txt
myNeurospydia.egg-info/requires.txt
myNeurospydia.egg-info/top_level.txt