Metadata-Version: 2.1
Name: myNeurospydia
Version: 0.1.19
Summary: Partially fixed version of Neuropsydia library, a Python module for creating experiments, tasks and questionnaires
Home-page: UNKNOWN
Author: Laborde
License: ENS_Paris_Saclay
Platform: UNKNOWN
